wbtest_utils
