Metadata-Version: 1.0
Name: wbtest-utils
Version: 0.0.2
Summary: 微博自动化测试工具
Home-page: https://gitlab.weibo.cn/andarchitecture/Android_AutoTest
Author: zhihui18
Author-email: zhihui18@staff.weibo.com
License: UNKNOWN
Platform: UNKNOWN
